{"cameraMode":{"drawMode":0,"name":"Shaded","section":"Shading Mode"},"sceneLighting":true,"audioPlay":false,"sceneViewState":{"showFog":true,"showMaterialUpdate":false,"showSkybox":true,"showFlares":true,"showImageEffects":true,"showParticleSystems":true},"in2DMode":false,"pivot":{"x":36.39677429199219,"y":3.1440000534057619,"z":25.95062828063965},"rotation":{"x":0.24230025708675385,"y":0.25041645765304568,"z":-0.06479313969612122,"w":0.9351804852485657},"size":0.6801079511642456,"orthographic":false}